functions_by_shukur/math-functions.py
functions_by_shukur-0.3.0.dist-info/WHEEL
functions_by_shukur-0.3.0.dist-info/METADATA
functions_by_shukur-0.3.0.dist-info/RECORD
