Metadata-Version: 2.1
Name: functions-by-shukur
Version: 0.3.0
Summary: THis is our test project
Author: Shukur Iminov
Author-email: ssean6754@gmail.com
Requires-Python: >=3.10,<4.0
Classifier: Programming Language :: Python :: 3
Classifier: Programming Language :: Python :: 3.10
Classifier: Programming Language :: Python :: 3.11
